Workbook

Sheet Summary
A1: Naina Kangan and Wool Store - Verified Summary (7 Feb 2024 to 31 Jan 2025)
A2: All figures are live formulas on the Data sheet (2,378 sales transactions). Blue cells on yellow are inputs/assumptions.
A3: Overall | B3: Value | C3: Note
A4: Sales transactions | B4: =COUNTA(Data!$A$2:$A$2379) -> 2378 | C4: Zero-revenue "Holiday" rows excluded (see Notes)
A5: Closed (zero-sale) days | B5: 46 | C5: Input: rows tagged Holiday in the source sheet; see data/closed_days.csv
A6: Total revenue (Rs) | B6: =SUM(Data!$J$2:$J$2379) -> 1219396
A7: Gross profit (Rs) | B7: =SUM(Data!$L$2:$L$2379) -> 265562
A8: Gross margin | B8: =B7/B6 -> 0.21778159
A9: Average revenue per transaction (Rs) | B9: =B6/B4 -> 512.78217 | C9: Earlier reports showed 503.05 because they divided by 2,424 rows incl. closed days
A10: Median transaction (Rs) | B10: =MEDIAN(Data!$J$2:$J$2379) -> 400
A11: Largest transaction (Rs) | B11: =MAX(Data!$J$2:$J$2379) -> 3250
A13: Category | B13: Transactions | C13: Revenue (Rs) | D13: Revenue share | E13: Gross profit (Rs) | F13: Gross margin | G13: Units sold*
A14: Bangles | B14: =COUNTIFS(Data!$D$2:$D$2379,$A14) -> 1415 | C14: =SUMIFS(Data!$J$2:$J$2379,Data!$D$2:$D$2379,$A14) -> 897620 | D14: =C14/$C$16 -> 0.73611854 | E14: =SUMIFS(Data!$L$2:$L$2379,Data!$D$2:$D$2379,$A14) -> 216920 | F14: =E14/C14 -> 0.24166128 | G14: =SUMIFS(Data!$F$2:$F$2379,Data!$D$2:$D$2379,$A14) -> 8574
A15: Wool | B15: =COUNTIFS(Data!$D$2:$D$2379,$A15) -> 963 | C15: =SUMIFS(Data!$J$2:$J$2379,Data!$D$2:$D$2379,$A15) -> 321776 | D15: =C15/$C$16 -> 0.26388146 | E15: =SUMIFS(Data!$L$2:$L$2379,Data!$D$2:$D$2379,$A15) -> 48642 | F15: =E15/C15 -> 0.15116727 | G15: =SUMIFS(Data!$F$2:$F$2379,Data!$D$2:$D$2379,$A15) -> 2199.25
A16: Total | B16: =SUM(B14:B15) -> 2378 | C16: =SUM(C14:C15) -> 1219396 | D16: =SUM(D14:D15) -> 1 | E16: =SUM(E14:E15) -> 265562 | F16: =E16/C16 -> 0.21778159 | G16: =SUM(G14:G15) -> 10773.25
A17: *Units are not comparable across categories (boxes vs yarn/pounds vs pieces); compare revenue instead.
A19: Customer type | B19: Transactions | C19: Revenue (Rs) | D19: Avg per transaction (Rs) | E19: Revenue share
A20: B2B | B20: =COUNTIFS(Data!$O$2:$O$2379,$A20) -> 1308 | C20: =SUMIFS(Data!$J$2:$J$2379,Data!$O$2:$O$2379,$A20) -> 828020 | D20: =C20/B20 -> 633.04281 | E20: =C20/$C$22 -> 0.6790411
A21: B2C | B21: =COUNTIFS(Data!$O$2:$O$2379,$A21) -> 1070 | C21: =SUMIFS(Data!$J$2:$J$2379,Data!$O$2:$O$2379,$A21) -> 391376 | D21: =C21/B21 -> 365.77196 | E21: =C21/$C$22 -> 0.3209589
A22: Total | B22: =SUM(B20:B21) -> 2378 | C22: =SUM(C20:C21) -> 1219396 | D22: =C22/B22 -> 512.78217 | E22: =SUM(E20:E21) -> 1
A24: Payment mode | B24: Transactions | C24: Share of transactions | D24: Revenue (Rs) | E24: Share of revenue
A25: Cash | B25: =COUNTIFS(Data!$P$2:$P$2379,$A25) -> 2252 | C25: =B25/$B$27 -> 0.9470143 | D25: =SUMIFS(Data!$J$2:$J$2379,Data!$P$2:$P$2379,$A25) -> 1173904 | E25: =D25/$D$27 -> 0.96269301
A26: Online | B26: =COUNTIFS(Data!$P$2:$P$2379,$A26) -> 126 | C26: =B26/$B$27 -> 0.052985702 | D26: =SUMIFS(Data!$J$2:$J$2379,Data!$P$2:$P$2379,$A26) -> 45492 | E26: =D26/$D$27 -> 0.037306995
A27: Total | B27: =SUM(B25:B26) -> 2378 | C27: =SUM(C25:C26) -> 1 | D27: =SUM(D25:D26) -> 1219396 | E27: =SUM(E25:E26) -> 1
A29: Revenue concentration | B29: Value | C29: Note
A30: Revenue share of top 10% of transactions | B30: =SUMPRODUCT(LARGE(Data!$J$2:$J$2379,ROW($1:$238)))/B6 -> 0.28788023 | C30: Top 238 transactions
A31: Revenue share of top 20% of transactions | B31: =SUMPRODUCT(LARGE(Data!$J$2:$J$2379,ROW($1:$476)))/B6 -> 0.44613071 | C31: Top 476 transactions
A32: Share of transactions needed to reach 80% of revenue | B32: =(COUNTIF(Pareto!D2:D2379,"<0.8")+1)/B4 -> 0.53574432 | C32: Not a classic 80/20 pattern
A33: Transactions of Rs 1,000 or more | B33: =COUNTIF(Data!$J$2:$J$2379,">=1000") -> 224
A34: Their share of total revenue | B34: =SUMIF(Data!$J$2:$J$2379,">=1000")/B6 -> 0.27691578
A36: Bin from (Rs) | B36: Bin to (Rs) | C36: Label | D36: Transactions
A37: 0 | B37: 500 | C37: =A37&"-"&(B37-1) -> 0-499 | D37: =COUNTIFS(Data!$J$2:$J$2379,">="&A37,Data!$J$2:$J$2379,"<"&B37) -> 1325
A38: 500 | B38: 1000 | C38: =A38&"-"&(B38-1) -> 500-999 | D38: =COUNTIFS(Data!$J$2:$J$2379,">="&A38,Data!$J$2:$J$2379,"<"&B38) -> 829
A39: 1000 | B39: 1500 | C39: =A39&"-"&(B39-1) -> 1000-1499 | D39: =COUNTIFS(Data!$J$2:$J$2379,">="&A39,Data!$J$2:$J$2379,"<"&B39) -> 125
A40: 1500 | B40: 2000 | C40: =A40&"-"&(B40-1) -> 1500-1999 | D40: =COUNTIFS(Data!$J$2:$J$2379,">="&A40,Data!$J$2:$J$2379,"<"&B40) -> 60
A41: 2000 | B41: 2500 | C41: =A41&"-"&(B41-1) -> 2000-2499 | D41: =COUNTIFS(Data!$J$2:$J$2379,">="&A41,Data!$J$2:$J$2379,"<"&B41) -> 32
A42: 2500 | B42: 3000 | C42: =A42&"-"&(B42-1) -> 2500-2999 | D42: =COUNTIFS(Data!$J$2:$J$2379,">="&A42,Data!$J$2:$J$2379,"<"&B42) -> 4
A43: 3000 | B43: 3500 | C43: =A43&"-"&(B43-1) -> 3000-3499 | D43: =COUNTIFS(Data!$J$2:$J$2379,">="&A43,Data!$J$2:$J$2379,"<"&B43) -> 3
C44: Total | D44: =SUM(D37:D43) -> 2378

Sheet Data
A1: Txn ID | B1: Date | C1: Month | D1: Product Category | E1: Product Type | F1: Quantity | G1: Unit Type | H1: Price per Unit | I1: Cost per Unit | J1: Revenue | K1: Total Cost | L1: Gross Profit | M1: Profit Margin % | N1: Season | O1: Customer Type | P1: Payment Mode
A2: 1 | B2: 45329 | C2: February | D2: Wool | E2: Baby Soft Wool | F2: 3 | G2: Jar | H2: 200 | I2: 160 | J2: 600 | K2: 480 | L2: 120 | M2: 25 | N2: Winter | O2: B2C | P2: Online
A3: 2 | B3: 45329 | C3: February | D3: Bangles | E3: Bangles Box | F3: 3 | G3: Box | H3: 130 | I3: 100 | J3: 390 | K3: 300 | L3: 90 | M3: 30 | N3: Winter | O3: B2B | P3: Cash
A4: 3 | B4: 45329 | C4: February | D4: Bangles | E4: Bangles Box (Plus size) | F4: 3 | G4: Box | H4: 150 | I4: 100 | J4: 450 | K4: 300 | L4: 150 | M4: 50 | N4: Winter | O4: B2C | P4: Cash
A5: 4 | B5: 45329 | C5: February | D5: Wool | E5: Wool Ball(q2) | F5: 2 | G5: Yarn | H5: 280 | I5: 240 | J5: 560 | K5: 480 | L5: 80 | M5: 16.666667 | N5: Winter | O5: B2C | P5: Cash
A6: 5 | B6: 45329 | C6: February | D6: Wool | E6: Wool Ball(q2) | F6: 2 | G6: Yarn | H6: 280 | I6: 240 | J6: 560 | K6: 480 | L6: 80 | M6: 16.666667 | N6: Winter | O6: B2C | P6: Online
A7: 6 | B7: 45330 | C7: February | D7: Wool | E7: Wool Ball Packet | F7: 1 | G7: Packet | H7: 300 | I7: 265 | J7: 300 | K7: 265 | L7: 35 | M7: 13.207547 | N7: Winter | O7: B2C | P7: Online
A8: 7 | B8: 45330 | C8: February | D8: Wool | E8: Baby Soft Wool | F8: 1 | G8: Jar | H8: 200 | I8: 160 | J8: 200 | K8: 160 | L8: 40 | M8: 25 | N8: Winter | O8: B2C | P8: Cash
A9: 8 | B9: 45330 | C9: February | D9: Wool | E9: Wool Ball(q2) | F9: 3 | G9: Yarn | H9: 280 | I9: 240 | J9: 840 | K9: 720 | L9: 120 | M9: 16.666667 | N9: Winter | O9: B2C | P9: Cash
A10: 9 | B10: 45330 | C10: February | D10: Wool | E10: Wool Ball(q1) | F10: 1 | G10: Yarn | H10: 260 | I10: 220 | J10: 260 | K10: 220 | L10: 40 | M10: 18.181818 | N10: Winter | O10: B2C | P10: Cash
A11: 10 | B11: 45331 | C11: February | D11: Bangles | E11: Bangles Box | F11: 3 | G11: Box | H11: 130 | I11: 100 | J11: 390 | K11: 300 | L11: 90 | M11: 30 | N11: Winter | O11: B2B | P11: Cash
A12: 11 | B12: 45331 | C12: February | D12: Wool | E12: Wool Ball(q2) | F12: 2 | G12: Yarn | H12: 280 | I12: 240 | J12: 560 | K12: 480 | L12: 80 | M12: 16.666667 | N12: Winter | O12: B2C | P12: Cash
A13: 12 | B13: 45331 | C13: February | D13: Wool | E13: Wool Ball Packet | F13: 2 | G13: Packet | H13: 300 | I13: 265 | J13: 600 | K13: 530 | L13: 70 | M13: 13.207547 | N13: Winter | O13: B2C | P13: Cash
... A2379: 2378 | B2379: 45688 | C2379: January | D2379: Wool | E2379: Wool Ball(q2) | F2379: 3 | G2379: Yarn | H2379: 280 | I2379: 240 | J2379: 840 | K2379: 720 | L2379: 120 | M2379: 16.666667 | N2379: Winter | O2379: B2C | P2379: Cash

Sheet Data 1
A1: Date | B1: Month | C1: Sales | N1: Cost Price | Y1: Selling Price | AJ1: Revenue | AU1: Gross Profit
C2: Bangles | H2: Wool | N2: Bangles | S2: Wool | Y2: Bangles | AD2: Wool | AJ2: Bangles | AO2: Wool | AU2: Bangles | AZ2: Wool
C3: Bangles Box | D3: Bangles Box (Plus size) | E3: Fancy Bangles Box | F3: Metal Bangles(Box) | G3: Bangles Set(Box) | H3: Wool Ball(q1) | I3: Wool Ball(q2) | J3: Baby Soft Wool | K3: Knitting Needle(Pair) | L3: Button(Pieces) | M3: Wool Ball Packet | N3: Bangles Box | O3: Bangles Box (Plus size) | P3: Fancy Bangles Box | Q3: Metal Bangles(Box) | R3: Bangles Set(Box) | S3: Wool Ball(q1) | T3: Wool Ball(q2) | U3: Baby Soft Wool | V3: Knitting Needle(Pair) | W3: Button(Pieces) | X3: Wool Ball Packet | Y3: Bangles Box | Z3: Bangles Box (Plus size) | AA3: Fancy Bangles Box | AB3: Metal Bangles(Box) | AC3: Bangles Set(Box) | AD3: Wool Ball(q1) | AE3: Wool Ball(q2) | AF3: Baby Soft Wool | AG3: Knitting Needle(Pair) | AH3: Button(Pieces) | AI3: Wool Ball Packet | AJ3: Bangles Box | AK3: Bangles Box (Plus size) | AL3: Fancy Bangles Box | AM3: Metal Bangles(Box) | AN3: Bangles Set(Box) | AO3: Wool Ball(q1) | AP3: Wool Ball(q2) | AQ3: Baby Soft Wool | AR3: Knitting Needle(Pair) | AS3: Button(Pieces) | AT3: Wool Ball Packet | AU3: Bangles Box | AV3: Bangles Box (Plus size) | AW3: Fancy Bangles Box | AX3: Metal Bangles(Box) | AY3: Bangles Set(Box) | AZ3: Wool Ball(q1) | BA3: Wool Ball(q2) | BB3: Baby Soft Wool | BC3: Knitting Needle(Pair) | BD3: Button(Pieces) | BE3: Wool Ball Packet | BF3: Total Gross Profit | BG3: Season
A4: 45329 | B4: =TEXT(A4,"mmmm") -> February | C4: 3 | D4: 0 | E4: 0 | F4: 0 | G4: 0 | H4: 0 | I4: 4 | J4: 3 | K4: 0 | L4: 0 | M4: 0 | N4: 110 | O4: 110 | P4: 26 | Q4: 65 | R4: 200 | S4: 230 | T4: 250 | U4: 170 | V4: 25 | W4: 4 | X4: 265 | Y4: 130 | Z4: 150 | AA4: 30 | AB4: 95 | AC4: 250 | AD4: 260 | AE4: 280 | AF4: 200 | AG4: 30 | AH4: 6 | AI4: 300 | AJ4: =Y4*C4 -> 390 | AK4: =D4*Z4 -> 0 | AL4: =E4*AA4 -> 0 | AM4: =F4*AB4 -> 0 | AN4: =G4*AC4 -> 0 | AO4: =H4*AD4 -> 0 | AP4: =I4*AE4 -> 1120 | AQ4: =J4*AF4 -> 600 | AR4: =K4*AG4 -> 0 | ... AT4: =M4*AI4 -> 0 | AU4: =AJ4-(C4*N4) -> 60 | AV4: =AK4-(D4*O4) -> 0 | AW4: =AL4-(E4*P4) -> 0 | AX4: =AM4-(F4*Q4) -> 0 | AY4: =AN4-(G4*R4) -> 0 | AZ4: =AO4-(H4*S4) -> 0 | BA4: =AP4-(I4*T4) -> 120 | BB4: =AQ4-(J4*U4) -> 90 | ... BE4: =AT4-(M4*X4) -> 0 | BF4: =SUM(AU4:BE4) -> 270 | BG4: {=_xlfn.IFS( OR(MONTH(A4)=11,MONTH(A4)=12,MONTH(A4)=1,MONTH(A4)=2),"Winter", OR(MONTH(A4)=3,MONTH(A4)=4),"Spring", OR(MONTH(A4)=5,MONTH(A4)=6),"Summer", OR(MONTH(A4)=7,MONTH(A4)=8,MONTH(A4)=9),"Monsoon", MONTH(A4)=10,"Autumn/Festive", TRUE,"" )} -> Winter
A5: 45330 | B5: =TEXT(A5,"mmmm") -> February | C5: 0 | D5: 0 | E5: 0 | F5: 0 | G5: 0 | H5: 1 | I5: 3 | J5: 1 | K5: 0 | L5: 0 | M5: 1 | N5: 110 | O5: 110 | P5: 26 | Q5: 65 | R5: 200 | S5: 230 | T5: 250 | U5: 170 | V5: 25 | W5: 4 | X5: 265 | Y5: 130 | Z5: 150 | AA5: 30 | AB5: 95 | AC5: 250 | AD5: 260 | AE5: 280 | AF5: 200 | AG5: 30 | AH5: 6 | AI5: 300 | AJ5: =Y5*C5 -> 0 | AK5: =D5*Z5 -> 0 | AL5: =E5*AA5 -> 0 | AM5: =F5*AB5 -> 0 | AN5: =G5*AC5 -> 0 | AO5: =H5*AD5 -> 260 | AP5: =I5*AE5 -> 840 | AQ5: =J5*AF5 -> 200 | AR5: =K5*AG5 -> 0 | ... AT5: =M5*AI5 -> 300 | AU5: =AJ5-(C5*N5) -> 0 | AV5: =AK5-(D5*O5) -> 0 | AW5: =AL5-(E5*P5) -> 0 | AX5: =AM5-(F5*Q5) -> 0 | AY5: =AN5-(G5*R5) -> 0 | AZ5: =AO5-(H5*S5) -> 30 | BA5: =AP5-(I5*T5) -> 90 | BB5: =AQ5-(J5*U5) -> 30 | ... BE5: =AT5-(M5*X5) -> 35 | BF5: =SUM(AU5:BE5) -> 185 | BG5: {=_xlfn.IFS( OR(MONTH(A5)=11,MONTH(A5)=12,MONTH(A5)=1,MONTH(A5)=2),"Winter", OR(MONTH(A5)=3,MONTH(A5)=4),"Spring", OR(MONTH(A5)=5,MONTH(A5)=6),"Summer", OR(MONTH(A5)=7,MONTH(A5)=8,MONTH(A5)=9),"Monsoon", MONTH(A5)=10,"Autumn/Festive", TRUE,"" )} -> Winter
A6: 45331 | B6: =TEXT(A6,"mmmm") -> February | C6: 4 | D6: 1 | E6: 2 | F6: 0 | G6: 0 | H6: 3 | I6: 10.5 | J6: 2 | K6: 1 | L6: 0 | M6: 4 | N6: 110 | O6: 110 | P6: 26 | Q6: 65 | R6: 200 | S6: 230 | T6: 250 | U6: 170 | V6: 25 | W6: 4 | X6: 265 | Y6: 130 | Z6: 150 | AA6: 30 | AB6: 95 | AC6: 250 | AD6: 260 | AE6: 280 | AF6: 200 | AG6: 30 | AH6: 6 | AI6: 300 | AJ6: =Y6*C6 -> 520 | AK6: =D6*Z6 -> 150 | AL6: =E6*AA6 -> 60 | AM6: =F6*AB6 -> 0 | AN6: =G6*AC6 -> 0 | AO6: =H6*AD6 -> 780 | AP6: =I6*AE6 -> 2940 | AQ6: =J6*AF6 -> 400 | AR6: =K6*AG6 -> 30 | ... AT6: =M6*AI6 -> 1200 | AU6: =AJ6-(C6*N6) -> 80 | AV6: =AK6-(D6*O6) -> 40 | AW6: =AL6-(E6*P6) -> 8 | AX6: =AM6-(F6*Q6) -> 0 | AY6: =AN6-(G6*R6) -> 0 | AZ6: =AO6-(H6*S6) -> 90 | BA6: =AP6-(I6*T6) -> 315 | BB6: =AQ6-(J6*U6) -> 60 | ... BE6: =AT6-(M6*X6) -> 140 | BF6: =SUM(AU6:BE6) -> 738 | BG6: {=_xlfn.IFS( OR(MONTH(A6)=11,MONTH(A6)=12,MONTH(A6)=1,MONTH(A6)=2),"Winter", OR(MONTH(A6)=3,MONTH(A6)=4),"Spring", OR(MONTH(A6)=5,MONTH(A6)=6),"Summer", OR(MONTH(A6)=7,MONTH(A6)=8,MONTH(A6)=9),"Monsoon", MONTH(A6)=10,"Autumn/Festive", TRUE,"" )} -> Winter
A7: 45332 | B7: =TEXT(A7,"mmmm") -> February | C7: 4 | D7: 0 | E7: 0 | F7: 0 | G7: 0 | H7: 6 | I7: 3 | J7: 0 | K7: 0 | L7: 6 | M7: 0 | N7: 110 | O7: 110 | P7: 26 | Q7: 65 | R7: 200 | S7: 230 | T7: 250 | U7: 170 | V7: 25 | W7: 4 | X7: 265 | Y7: 130 | Z7: 150 | AA7: 30 | AB7: 95 | AC7: 250 | AD7: 260 | AE7: 280 | AF7: 200 | AG7: 30 | AH7: 6 | AI7: 300 | AJ7: =Y7*C7 -> 520 | AK7: =D7*Z7 -> 0 | AL7: =E7*AA7 -> 0 | AM7: =F7*AB7 -> 0 | AN7: =G7*AC7 -> 0 | AO7: =H7*AD7 -> 1560 | AP7: =I7*AE7 -> 840 | AQ7: =J7*AF7 -> 0 | AR7: =K7*AG7 -> 0 | ... AT7: =M7*AI7 -> 0 | AU7: =AJ7-(C7*N7) -> 80 | AV7: =AK7-(D7*O7) -> 0 | AW7: =AL7-(E7*P7) -> 0 | AX7: =AM7-(F7*Q7) -> 0 | AY7: =AN7-(G7*R7) -> 0 | AZ7: =AO7-(H7*S7) -> 180 | BA7: =AP7-(I7*T7) -> 90 | BB7: =AQ7-(J7*U7) -> 0 | ... BE7: =AT7-(M7*X7) -> 0 | BF7: =SUM(AU7:BE7) -> 362 | BG7: {=_xlfn.IFS( OR(MONTH(A7)=11,MONTH(A7)=12,MONTH(A7)=1,MONTH(A7)=2),"Winter", OR(MONTH(A7)=3,MONTH(A7)=4),"Spring", OR(MONTH(A7)=5,MONTH(A7)=6),"Summer", OR(MONTH(A7)=7,MONTH(A7)=8,MONTH(A7)=9),"Monsoon", MONTH(A7)=10,"Autumn/Festive", TRUE,"" )} -> Winter
A8: 45333 | B8: =TEXT(A8,"mmmm") -> February | C8: 6 | D8: 0 | E8: 0 | F8: 0 | G8: 0 | H8: 4.5 | I8: 6.5 | J8: 0 | K8: 4 | L8: 0 | M8: 1 | N8: 110 | O8: 110 | P8: 26 | Q8: 65 | R8: 200 | S8: 230 | T8: 250 | U8: 170 | V8: 25 | W8: 4 | X8: 265 | Y8: 130 | Z8: 150 | AA8: 30 | AB8: 95 | AC8: 250 | AD8: 260 | AE8: 280 | AF8: 200 | AG8: 30 | AH8: 6 | AI8: 300 | AJ8: =Y8*C8 -> 780 | AK8: =D8*Z8 -> 0 | AL8: =E8*AA8 -> 0 | AM8: =F8*AB8 -> 0 | AN8: =G8*AC8 -> 0 | AO8: =H8*AD8 -> 1170 | AP8: =I8*AE8 -> 1820 | AQ8: =J8*AF8 -> 0 | AR8: =K8*AG8 -> 120 | ... AT8: =M8*AI8 -> 300 | AU8: =AJ8-(C8*N8) -> 120 | AV8: =AK8-(D8*O8) -> 0 | AW8: =AL8-(E8*P8) -> 0 | AX8: =AM8-(F8*Q8) -> 0 | AY8: =AN8-(G8*R8) -> 0 | AZ8: =AO8-(H8*S8) -> 135 | BA8: =AP8-(I8*T8) -> 195 | BB8: =AQ8-(J8*U8) -> 0 | ... BE8: =AT8-(M8*X8) -> 35 | BF8: =SUM(AU8:BE8) -> 505 | BG8: {=_xlfn.IFS( OR(MONTH(A8)=11,MONTH(A8)=12,MONTH(A8)=1,MONTH(A8)=2),"Winter", OR(MONTH(A8)=3,MONTH(A8)=4),"Spring", OR(MONTH(A8)=5,MONTH(A8)=6),"Summer", OR(MONTH(A8)=7,MONTH(A8)=8,MONTH(A8)=9),"Monsoon", MONTH(A8)=10,"Autumn/Festive", TRUE,"" )} -> Winter
A9: 45334 | B9: =TEXT(A9,"mmmm") -> February | C9: 9 | D9: 0 | E9: 0 | F9: 0 | G9: 0 | H9: 6 | I9: 7 | J9: 0 | K9: 1 | L9: 0 | M9: 1 | N9: 110 | O9: 110 | P9: 26 | Q9: 65 | R9: 200 | S9: 230 | T9: 250 | U9: 170 | V9: 25 | W9: 4 | X9: 265 | Y9: 130 | Z9: 150 | AA9: 30 | AB9: 95 | AC9: 250 | AD9: 260 | AE9: 280 | AF9: 200 | AG9: 30 | AH9: 6 | AI9: 300 | AJ9: =Y9*C9 -> 1170 | AK9: =D9*Z9 -> 0 | AL9: =E9*AA9 -> 0 | AM9: =F9*AB9 -> 0 | AN9: =G9*AC9 -> 0 | AO9: =H9*AD9 -> 1560 | AP9: =I9*AE9 -> 1960 | AQ9: =J9*AF9 -> 0 | AR9: =K9*AG9 -> 30 | ... AT9: =M9*AI9 -> 300 | AU9: =AJ9-(C9*N9) -> 180 | AV9: =AK9-(D9*O9) -> 0 | AW9: =AL9-(E9*P9) -> 0 | AX9: =AM9-(F9*Q9) -> 0 | AY9: =AN9-(G9*R9) -> 0 | AZ9: =AO9-(H9*S9) -> 180 | BA9: =AP9-(I9*T9) -> 210 | BB9: =AQ9-(J9*U9) -> 0 | ... BE9: =AT9-(M9*X9) -> 35 | BF9: =SUM(AU9:BE9) -> 610 | BG9: {=_xlfn.IFS( OR(MONTH(A9)=11,MONTH(A9)=12,MONTH(A9)=1,MONTH(A9)=2),"Winter", OR(MONTH(A9)=3,MONTH(A9)=4),"Spring", OR(MONTH(A9)=5,MONTH(A9)=6),"Summer", OR(MONTH(A9)=7,MONTH(A9)=8,MONTH(A9)=9),"Monsoon", MONTH(A9)=10,"Autumn/Festive", TRUE,"" )} -> Winter
A10: 45335 | B10: =TEXT(A10,"mmmm") -> February | C10: 3 | D10: 4 | E10: 0 | F10: 2 | G10: 0 | H10: 3 | I10: 7 | J10: 0 | K10: 0 | L10: 0 | M10: 0 | N10: 110 | O10: 110 | P10: 26 | Q10: 65 | R10: 200 | S10: 230 | T10: 250 | U10: 170 | V10: 25 | W10: 4 | X10: 265 | Y10: 130 | Z10: 150 | AA10: 30 | AB10: 95 | AC10: 250 | AD10: 260 | AE10: 280 | AF10: 200 | AG10: 30 | AH10: 6 | AI10: 300 | AJ10: =Y10*C10 -> 390 | AK10: =D10*Z10 -> 600 | AL10: =E10*AA10 -> 0 | AM10: =F10*AB10 -> 190 | AN10: =G10*AC10 -> 0 | AO10: =H10*AD10 -> 780 | AP10: =I10*AE10 -> 1960 | AQ10: =J10*AF10 -> 0 | AR10: =K10*AG10 -> 0 | ... AT10: =M10*AI10 -> 0 | AU10: =AJ10-(C10*N10) -> 60 | AV10: =AK10-(D10*O10) -> 160 | AW10: =AL10-(E10*P10) -> 0 | AX10: =AM10-(F10*Q10) -> 60 | AY10: =AN10-(G10*R10) -> 0 | AZ10: =AO10-(H10*S10) -> 90 | BA10: =AP10-(I10*T10) -> 210 | BB10: =AQ10-(J10*U10) -> 0 | ... BE10: =AT10-(M10*X10) -> 0 | BF10: =SUM(AU10:BE10) -> 580 | BG10: {=_xlfn.IFS( OR(MONTH(A10)=11,MONTH(A10)=12,MONTH(A10)=1,MONTH(A10)=2),"Winter", OR(MONTH(A10)=3,MONTH(A10)=4),"Spring", OR(MONTH(A10)=5,MONTH(A10)=6),"Summer", OR(MONTH(A10)=7,MONTH(A10)=8,MONTH(A10)=9),"Monsoon", MONTH(A10)=10,"Autumn/Festive", TRUE,"" )} -> Winter
A11: 45336 | B11: =TEXT(A11,"mmmm") -> February | C11: 5 | D11: 0 | E11: 0 | F11: 0 | G11: 0 | H11: 4 | I11: 5 | J11: 0 | K11: 0 | L11: 0 | M11: 0 | N11: 110 | O11: 110 | P11: 26 | Q11: 65 | R11: 200 | S11: 230 | T11: 250 | U11: 170 | V11: 25 | W11: 4 | X11: 265 | Y11: 130 | Z11: 150 | AA11: 30 | AB11: 95 | AC11: 250 | AD11: 260 | AE11: 280 | AF11: 200 | AG11: 30 | AH11: 6 | AI11: 300 | AJ11: =Y11*C11 -> 650 | AK11: =D11*Z11 -> 0 | AL11: =E11*AA11 -> 0 | AM11: =F11*AB11 -> 0 | AN11: =G11*AC11 -> 0 | AO11: =H11*AD11 -> 1040 | AP11: =I11*AE11 -> 1400 | AQ11: =J11*AF11 -> 0 | AR11: =K11*AG11 -> 0 | ... AT11: =M11*AI11 -> 0 | AU11: =AJ11-(C11*N11) -> 100 | AV11: =AK11-(D11*O11) -> 0 | AW11: =AL11-(E11*P11) -> 0 | AX11: =AM11-(F11*Q11) -> 0 | AY11: =AN11-(G11*R11) -> 0 | AZ11: =AO11-(H11*S11) -> 120 | BA11: =AP11-(I11*T11) -> 150 | BB11: =AQ11-(J11*U11) -> 0 | ... BE11: =AT11-(M11*X11) -> 0 | BF11: =SUM(AU11:BE11) -> 370 | BG11: {=_xlfn.IFS( OR(MONTH(A11)=11,MONTH(A11)=12,MONTH(A11)=1,MONTH(A11)=2),"Winter", OR(MONTH(A11)=3,MONTH(A11)=4),"Spring", OR(MONTH(A11)=5,MONTH(A11)=6),"Summer", OR(MONTH(A11)=7,MONTH(A11)=8,MONTH(A11)=9),"Monsoon", MONTH(A11)=10,"Autumn/Festive", TRUE,"" )} -> Winter
A12: 45337 | B12: =TEXT(A12,"mmmm") -> February | C12: 10 | D12: 0 | E12: 0 | F12: 0 | G12: 0 | H12: 2.5 | I12: 3.5 | J12: 2 | K12: 2 | L12: 15 | M12: 1 | N12: 110 | O12: 110 | P12: 26 | Q12: 65 | R12: 200 | S12: 230 | T12: 250 | U12: 170 | V12: 25 | W12: 4 | X12: 265 | Y12: 130 | Z12: 150 | AA12: 30 | AB12: 95 | AC12: 250 | AD12: 260 | AE12: 280 | AF12: 200 | AG12: 30 | AH12: 6 | AI12: 300 | AJ12: =Y12*C12 -> 1300 | AK12: =D12*Z12 -> 0 | AL12: =E12*AA12 -> 0 | AM12: =F12*AB12 -> 0 | AN12: =G12*AC12 -> 0 | AO12: =H12*AD12 -> 650 | AP12: =I12*AE12 -> 980 | AQ12: =J12*AF12 -> 400 | AR12: =K12*AG12 -> 60 | ... AT12: =M12*AI12 -> 300 | AU12: =AJ12-(C12*N12) -> 200 | AV12: =AK12-(D12*O12) -> 0 | AW12: =AL12-(E12*P12) -> 0 | AX12: =AM12-(F12*Q12) -> 0 | AY12: =AN12-(G12*R12) -> 0 | AZ12: =AO12-(H12*S12) -> 75 | BA12: =AP12-(I12*T12) -> 105 | BB12: =AQ12-(J12*U12) -> 60 | ... BE12: =AT12-(M12*X12) -> 35 | BF12: =SUM(AU12:BE12) -> 515 | BG12: {=_xlfn.IFS( OR(MONTH(A12)=11,MONTH(A12)=12,MONTH(A12)=1,MONTH(A12)=2),"Winter", OR(MONTH(A12)=3,MONTH(A12)=4),"Spring", OR(MONTH(A12)=5,MONTH(A12)=6),"Summer", OR(MONTH(A12)=7,MONTH(A12)=8,MONTH(A12)=9),"Monsoon", MONTH(A12)=10,"Autumn/Festive", TRUE,"" )} -> Winter
A13: 45338 | B13: =TEXT(A13,"mmmm") -> February | C13: 3 | D13: 2 | E13: 0 | F13: 0 | G13: 0 | H13: 5 | I13: 6 | J13: 1 | K13: 0 | L13: 0 | M13: 0 | N13: 110 | O13: 110 | P13: 26 | Q13: 65 | R13: 200 | S13: 230 | T13: 250 | U13: 170 | V13: 25 | W13: 4 | X13: 265 | Y13: 130 | Z13: 150 | AA13: 30 | AB13: 95 | AC13: 250 | AD13: 260 | AE13: 280 | AF13: 200 | AG13: 30 | AH13: 6 | AI13: 300 | AJ13: =Y13*C13 -> 390 | AK13: =D13*Z13 -> 300 | AL13: =E13*AA13 -> 0 | AM13: =F13*AB13 -> 0 | AN13: =G13*AC13 -> 0 | AO13: =H13*AD13 -> 1300 | AP13: =I13*AE13 -> 1680 | AQ13: =J13*AF13 -> 200 | AR13: =K13*AG13 -> 0 | ... AT13: =M13*AI13 -> 0 | AU13: =AJ13-(C13*N13) -> 60 | AV13: =AK13-(D13*O13) -> 80 | AW13: =AL13-(E13*P13) -> 0 | AX13: =AM13-(F13*Q13) -> 0 | AY13: =AN13-(G13*R13) -> 0 | AZ13: =AO13-(H13*S13) -> 150 | BA13: =AP13-(I13*T13) -> 180 | BB13: =AQ13-(J13*U13) -> 30 | ... BE13: =AT13-(M13*X13) -> 0 | BF13: =SUM(AU13:BE13) -> 500 | BG13: {=_xlfn.IFS( OR(MONTH(A13)=11,MONTH(A13)=12,MONTH(A13)=1,MONTH(A13)=2),"Winter", OR(MONTH(A13)=3,MONTH(A13)=4),"Spring", OR(MONTH(A13)=5,MONTH(A13)=6),"Summer", OR(MONTH(A13)=7,MONTH(A13)=8,MONTH(A13)=9),"Monsoon", MONTH(A13)=10,"Autumn/Festive", TRUE,"" )} -> Winter
A14: 45339 | B14: =TEXT(A14,"mmmm") -> February | C14: 6 | D14: 0 | E14: 0 | F14: 0 | G14: 0 | H14: 4.5 | I14: 6 | J14: 1 | K14: 2 | L14: 0 | M14: 2 | N14: 110 | O14: 110 | P14: 26 | Q14: 65 | R14: 200 | S14: 230 | T14: 250 | U14: 170 | V14: 25 | W14: 4 | X14: 265 | Y14: 130 | Z14: 150 | AA14: 30 | AB14: 95 | AC14: 250 | AD14: 260 | AE14: 280 | AF14: 200 | AG14: 30 | AH14: 6 | AI14: 300 | AJ14: =Y14*C14 -> 780 | AK14: =D14*Z14 -> 0 | AL14: =E14*AA14 -> 0 | AM14: =F14*AB14 -> 0 | AN14: =G14*AC14 -> 0 | AO14: =H14*AD14 -> 1170 | AP14: =I14*AE14 -> 1680 | AQ14: =J14*AF14 -> 200 | AR14: =K14*AG14 -> 60 | ... AT14: =M14*AI14 -> 600 | AU14: =AJ14-(C14*N14) -> 120 | AV14: =AK14-(D14*O14) -> 0 | AW14: =AL14-(E14*P14) -> 0 | AX14: =AM14-(F14*Q14) -> 0 | AY14: =AN14-(G14*R14) -> 0 | AZ14: =AO14-(H14*S14) -> 135 | BA14: =AP14-(I14*T14) -> 180 | BB14: =AQ14-(J14*U14) -> 30 | ... BE14: =AT14-(M14*X14) -> 70 | BF14: =SUM(AU14:BE14) -> 545 | BG14: {=_xlfn.IFS( OR(MONTH(A14)=11,MONTH(A14)=12,MONTH(A14)=1,MONTH(A14)=2),"Winter", OR(MONTH(A14)=3,MONTH(A14)=4),"Spring", OR(MONTH(A14)=5,MONTH(A14)=6),"Summer", OR(MONTH(A14)=7,MONTH(A14)=8,MONTH(A14)=9),"Monsoon", MONTH(A14)=10,"Autumn/Festive", TRUE,"" )} -> Winter
A15: 45340 | B15: =TEXT(A15,"mmmm") -> February | C15: 7 | D15: 0 | E15: 0 | F15: 1 | G15: 0 | H15: 4 | I15: 4 | J15: 0 | K15: 0 | L15: 0 | M15: 0 | N15: 110 | O15: 110 | P15: 26 | Q15: 65 | R15: 200 | S15: 230 | T15: 250 | U15: 170 | V15: 25 | W15: 4 | X15: 265 | Y15: 130 | Z15: 150 | AA15: 30 | AB15: 95 | AC15: 250 | AD15: 260 | AE15: 280 | AF15: 200 | AG15: 30 | AH15: 6 | AI15: 300 | AJ15: =Y15*C15 -> 910 | AK15: =D15*Z15 -> 0 | AL15: =E15*AA15 -> 0 | AM15: =F15*AB15 -> 95 | AN15: =G15*AC15 -> 0 | AO15: =H15*AD15 -> 1040 | AP15: =I15*AE15 -> 1120 | AQ15: =J15*AF15 -> 0 | AR15: =K15*AG15 -> 0 | ... AT15: =M15*AI15 -> 0 | AU15: =AJ15-(C15*N15) -> 140 | AV15: =AK15-(D15*O15) -> 0 | AW15: =AL15-(E15*P15) -> 0 | AX15: =AM15-(F15*Q15) -> 30 | AY15: =AN15-(G15*R15) -> 0 | AZ15: =AO15-(H15*S15) -> 120 | BA15: =AP15-(I15*T15) -> 120 | BB15: =AQ15-(J15*U15) -> 0 | ... BE15: =AT15-(M15*X15) -> 0 | BF15: =SUM(AU15:BE15) -> 410 | BG15: {=_xlfn.IFS( OR(MONTH(A15)=11,MONTH(A15)=12,MONTH(A15)=1,MONTH(A15)=2),"Winter", OR(MONTH(A15)=3,MONTH(A15)=4),"Spring", OR(MONTH(A15)=5,MONTH(A15)=6),"Summer", OR(MONTH(A15)=7,MONTH(A15)=8,MONTH(A15)=9),"Monsoon", MONTH(A15)=10,"Autumn/Festive", TRUE,"" )} -> Winter
... A363: 45688 | B363: =TEXT(A363,"mmmm") -> January | C363: 4 | D363: 1 | E363: 0 | F363: 0 | G363: 0 | H363: 2.75 | I363: 5.5 | J363: 0 | K363: 2 | L363: 14 | M363: 3 | N363: 110 | O363: 110 | P363: 26 | Q363: 65 | R363: 200 | S363: 230 | T363: 250 | U363: 170 | V363: 25 | W363: 4 | X363: 265 | Y363: 130 | Z363: 150 | AA363: 30 | AB363: 95 | AC363: 250 | AD363: 260 | AE363: 280 | AF363: 200 | AG363: 30 | AH363: 6 | AI363: 300 | AJ363: =Y363*C363 -> 520 | AK363: =D363*Z363 -> 150 | AL363: =E363*AA363 -> 0 | AM363: =F363*AB363 -> 0 | AN363: =G363*AC363 -> 0 | AO363: =H363*AD363 -> 715 | AP363: =I363*AE363 -> 1540 | AQ363: =J363*AF363 -> 0 | AR363: =K363*AG363 -> 60 | ... AT363: =M363*AI363 -> 900 | AU363: =AJ363-(C363*N363) -> 80 | AV363: =AK363-(D363*O363) -> 40 | AW363: =AL363-(E363*P363) -> 0 | AX363: =AM363-(F363*Q363) -> 0 | AY363: =AN363-(G363*R363) -> 0 | AZ363: =AO363-(H363*S363) -> 82.5 | BA363: =AP363-(I363*T363) -> 165 | BB363: =AQ363-(J363*U363) -> 0 | ... BE363: =AT363-(M363*X363) -> 105 | BF363: =SUM(AU363:BE363) -> 510.5 | BG363: {=_xlfn.IFS( OR(MONTH(A363)=11,MONTH(A363)=12,MONTH(A363)=1,MONTH(A363)=2),"Winter", OR(MONTH(A363)=3,MONTH(A363)=4),"Spring", OR(MONTH(A363)=5,MONTH(A363)=6),"Summer", OR(MONTH(A363)=7,MONTH(A363)=8,MONTH(A363)=9),"Monsoon", MONTH(A363)=10,"Autumn/Festive", TRUE,"" )} -> Winter

Sheet Monthly
A1: Month | B1: Season | C1: Bangles revenue | D1: Wool revenue | E1: Total revenue | F1: Gross profit | G1: Transactions | H1: Avg revenue / transaction | I1: Seasonal index
A2: February | B2: Winter | C2: =SUMIFS(Data!$J$2:$J$2379,Data!$C$2:$C$2379,$A2,Data!$D$2:$D$2379,"Bangles") -> 22940 | D2: =SUMIFS(Data!$J$2:$J$2379,Data!$C$2:$C$2379,$A2,Data!$D$2:$D$2379,"Wool") -> 60456 | E2: =C2+D2 -> 83396 | F2: =SUMIFS(Data!$L$2:$L$2379,Data!$C$2:$C$2379,$A2) -> 14990 | G2: =COUNTIFS(Data!$C$2:$C$2379,$A2) -> 168 | H2: =E2/G2 -> 496.40476 | I2: =E2/AVERAGE($E$2:$E$13) -> 0.82069484
A3: March | B3: Spring | C3: =SUMIFS(Data!$J$2:$J$2379,Data!$C$2:$C$2379,$A3,Data!$D$2:$D$2379,"Bangles") -> 33240 | D3: =SUMIFS(Data!$J$2:$J$2379,Data!$C$2:$C$2379,$A3,Data!$D$2:$D$2379,"Wool") -> 57798 | E3: =C3+D3 -> 91038 | F3: =SUMIFS(Data!$L$2:$L$2379,Data!$C$2:$C$2379,$A3) -> 16574 | G3: =COUNTIFS(Data!$C$2:$C$2379,$A3) -> 187 | H3: =E3/G3 -> 486.83422 | I3: =E3/AVERAGE($E$2:$E$13) -> 0.89589928
A4: April | B4: Spring | C4: =SUMIFS(Data!$J$2:$J$2379,Data!$C$2:$C$2379,$A4,Data!$D$2:$D$2379,"Bangles") -> 59295 | D4: =SUMIFS(Data!$J$2:$J$2379,Data!$C$2:$C$2379,$A4,Data!$D$2:$D$2379,"Wool") -> 14460 | E4: =C4+D4 -> 73755 | F4: =SUMIFS(Data!$L$2:$L$2379,Data!$C$2:$C$2379,$A4) -> 16300 | G4: =COUNTIFS(Data!$C$2:$C$2379,$A4) -> 144 | H4: =E4/G4 -> 512.1875 | I4: =E4/AVERAGE($E$2:$E$13) -> 0.72581836
A5: May | B5: Summer | C5: =SUMIFS(Data!$J$2:$J$2379,Data!$C$2:$C$2379,$A5,Data!$D$2:$D$2379,"Bangles") -> 56535 | D5: =SUMIFS(Data!$J$2:$J$2379,Data!$C$2:$C$2379,$A5,Data!$D$2:$D$2379,"Wool") -> 880 | E5: =C5+D5 -> 57415 | F5: =SUMIFS(Data!$L$2:$L$2379,Data!$C$2:$C$2379,$A5) -> 13972 | G5: =COUNTIFS(Data!$C$2:$C$2379,$A5) -> 97 | H5: =E5/G5 -> 591.90722 | I5: =E5/AVERAGE($E$2:$E$13) -> 0.56501743
A6: June | B6: Summer | C6: =SUMIFS(Data!$J$2:$J$2379,Data!$C$2:$C$2379,$A6,Data!$D$2:$D$2379,"Bangles") -> 61415 | D6: =SUMIFS(Data!$J$2:$J$2379,Data!$C$2:$C$2379,$A6,Data!$D$2:$D$2379,"Wool") -> 1000 | E6: =C6+D6 -> 62415 | F6: =SUMIFS(Data!$L$2:$L$2379,Data!$C$2:$C$2379,$A6) -> 15472 | G6: =COUNTIFS(Data!$C$2:$C$2379,$A6) -> 110 | H6: =E6/G6 -> 567.40909 | I6: =E6/AVERAGE($E$2:$E$13) -> 0.61422212
A7: July | B7: Monsoon | C7: =SUMIFS(Data!$J$2:$J$2379,Data!$C$2:$C$2379,$A7,Data!$D$2:$D$2379,"Bangles") -> 208060 | D7: =SUMIFS(Data!$J$2:$J$2379,Data!$C$2:$C$2379,$A7,Data!$D$2:$D$2379,"Wool") -> 1510 | E7: =C7+D7 -> 209570 | F7: =SUMIFS(Data!$L$2:$L$2379,Data!$C$2:$C$2379,$A7) -> 51285 | G7: =COUNTIFS(Data!$C$2:$C$2379,$A7) -> 272 | H7: =E7/G7 -> 770.47794 | I7: =E7/AVERAGE($E$2:$E$13) -> 2.0623653
A8: August | B8: Monsoon | C8: =SUMIFS(Data!$J$2:$J$2379,Data!$C$2:$C$2379,$A8,Data!$D$2:$D$2379,"Bangles") -> 86650 | D8: =SUMIFS(Data!$J$2:$J$2379,Data!$C$2:$C$2379,$A8,Data!$D$2:$D$2379,"Wool") -> 300 | E8: =C8+D8 -> 86950 | F8: =SUMIFS(Data!$L$2:$L$2379,Data!$C$2:$C$2379,$A8) -> 20973 | G8: =COUNTIFS(Data!$C$2:$C$2379,$A8) -> 129 | H8: =E8/G8 -> 674.03101 | I8: =E8/AVERAGE($E$2:$E$13) -> 0.85566953
A9: September | B9: Monsoon | C9: =SUMIFS(Data!$J$2:$J$2379,Data!$C$2:$C$2379,$A9,Data!$D$2:$D$2379,"Bangles") -> 19780 | D9: =SUMIFS(Data!$J$2:$J$2379,Data!$C$2:$C$2379,$A9,Data!$D$2:$D$2379,"Wool") -> 5210 | E9: =C9+D9 -> 24990 | F9: =SUMIFS(Data!$L$2:$L$2379,Data!$C$2:$C$2379,$A9) -> 5579 | G9: =COUNTIFS(Data!$C$2:$C$2379,$A9) -> 63 | H9: =E9/G9 -> 396.66667 | I9: =E9/AVERAGE($E$2:$E$13) -> 0.24592503
A10: October | B10: Autumn/Festive | C10: =SUMIFS(Data!$J$2:$J$2379,Data!$C$2:$C$2379,$A10,Data!$D$2:$D$2379,"Bangles") -> 291225 | D10: =SUMIFS(Data!$J$2:$J$2379,Data!$C$2:$C$2379,$A10,Data!$D$2:$D$2379,"Wool") -> 28672 | E10: =C10+D10 -> 319897 | F10: =SUMIFS(Data!$L$2:$L$2379,Data!$C$2:$C$2379,$A10) -> 73554 | G10: =COUNTIFS(Data!$C$2:$C$2379,$A10) -> 457 | H10: =E10/G10 -> 699.99344 | I10: =E10/AVERAGE($E$2:$E$13) -> 3.1480864
A11: November | B11: Winter | C11: =SUMIFS(Data!$J$2:$J$2379,Data!$C$2:$C$2379,$A11,Data!$D$2:$D$2379,"Bangles") -> 17370 | D11: =SUMIFS(Data!$J$2:$J$2379,Data!$C$2:$C$2379,$A11,Data!$D$2:$D$2379,"Wool") -> 37708 | E11: =C11+D11 -> 55078 | F11: =SUMIFS(Data!$L$2:$L$2379,Data!$C$2:$C$2379,$A11) -> 10227.5 | G11: =COUNTIFS(Data!$C$2:$C$2379,$A11) -> 199 | H11: =E11/G11 -> 276.77387 | I11: =E11/AVERAGE($E$2:$E$13) -> 0.54201916
A12: December | B12: Winter | C12: =SUMIFS(Data!$J$2:$J$2379,Data!$C$2:$C$2379,$A12,Data!$D$2:$D$2379,"Bangles") -> 16630 | D12: =SUMIFS(Data!$J$2:$J$2379,Data!$C$2:$C$2379,$A12,Data!$D$2:$D$2379,"Wool") -> 55102 | E12: =C12+D12 -> 71732 | F12: =SUMIFS(Data!$L$2:$L$2379,Data!$C$2:$C$2379,$A12) -> 12082.5 | G12: =COUNTIFS(Data!$C$2:$C$2379,$A12) -> 280 | H12: =E12/G12 -> 256.18571 | I12: =E12/AVERAGE($E$2:$E$13) -> 0.70591014
A13: January | B13: Winter | C13: =SUMIFS(Data!$J$2:$J$2379,Data!$C$2:$C$2379,$A13,Data!$D$2:$D$2379,"Bangles") -> 24480 | D13: =SUMIFS(Data!$J$2:$J$2379,Data!$C$2:$C$2379,$A13,Data!$D$2:$D$2379,"Wool") -> 58680 | E13: =C13+D13 -> 83160 | F13: =SUMIFS(Data!$L$2:$L$2379,Data!$C$2:$C$2379,$A13) -> 14553 | G13: =COUNTIFS(Data!$C$2:$C$2379,$A13) -> 272 | H13: =E13/G13 -> 305.73529 | I13: =E13/AVERAGE($E$2:$E$13) -> 0.81837237
A14: Total | C14: =SUM(C2:C13) -> 897620 | D14: =SUM(D2:D13) -> 321776 | E14: =SUM(E2:E13) -> 1219396 | F14: =SUM(F2:F13) -> 265562 | G14: =SUM(G2:G13) -> 2378 | H14: =E14/G14 -> 512.78217 | I14: =AVERAGE(I2:I13) -> 1
A16: Seasonal index = month revenue / average monthly revenue (1.00 = average month). Use it to time purchasing: >1.5 = peak, <0.6 = lean.
A17: Caution: one year of data only, so the index describes this year, not a validated forecast. Collect a second year before relying on it.

Sheet Seasonal
A1: Season | B1: Months in season | C1: Revenue | D1: Bangles revenue | E1: Wool revenue | F1: Gross profit | G1: Revenue per month | H1: Share of annual revenue | I1: Wool share of season revenue
A2: Autumn/Festive | B2: 1 | C2: =SUMIFS(Data!$J$2:$J$2379,Data!$N$2:$N$2379,$A2) -> 319897 | D2: =SUMIFS(Data!$J$2:$J$2379,Data!$N$2:$N$2379,$A2,Data!$D$2:$D$2379,"Bangles") -> 291225 | E2: =SUMIFS(Data!$J$2:$J$2379,Data!$N$2:$N$2379,$A2,Data!$D$2:$D$2379,"Wool") -> 28672 | F2: =SUMIFS(Data!$L$2:$L$2379,Data!$N$2:$N$2379,$A2) -> 73554 | G2: =C2/B2 -> 319897 | H2: =C2/$C$7 -> 0.26234054 | I2: =E2/C2 -> 0.089628849
A3: Monsoon | B3: 3 | C3: =SUMIFS(Data!$J$2:$J$2379,Data!$N$2:$N$2379,$A3) -> 321510 | D3: =SUMIFS(Data!$J$2:$J$2379,Data!$N$2:$N$2379,$A3,Data!$D$2:$D$2379,"Bangles") -> 314490 | E3: =SUMIFS(Data!$J$2:$J$2379,Data!$N$2:$N$2379,$A3,Data!$D$2:$D$2379,"Wool") -> 7020 | F3: =SUMIFS(Data!$L$2:$L$2379,Data!$N$2:$N$2379,$A3) -> 77837 | G3: =C3/B3 -> 107170 | H3: =C3/$C$7 -> 0.26366332 | I3: =E3/C3 -> 0.021834469
A4: Spring | B4: 2 | C4: =SUMIFS(Data!$J$2:$J$2379,Data!$N$2:$N$2379,$A4) -> 164793 | D4: =SUMIFS(Data!$J$2:$J$2379,Data!$N$2:$N$2379,$A4,Data!$D$2:$D$2379,"Bangles") -> 92535 | E4: =SUMIFS(Data!$J$2:$J$2379,Data!$N$2:$N$2379,$A4,Data!$D$2:$D$2379,"Wool") -> 72258 | F4: =SUMIFS(Data!$L$2:$L$2379,Data!$N$2:$N$2379,$A4) -> 32874 | G4: =C4/B4 -> 82396.5 | H4: =C4/$C$7 -> 0.13514314 | I4: =E4/C4 -> 0.43847736
A5: Summer | B5: 2 | C5: =SUMIFS(Data!$J$2:$J$2379,Data!$N$2:$N$2379,$A5) -> 119830 | D5: =SUMIFS(Data!$J$2:$J$2379,Data!$N$2:$N$2379,$A5,Data!$D$2:$D$2379,"Bangles") -> 117950 | E5: =SUMIFS(Data!$J$2:$J$2379,Data!$N$2:$N$2379,$A5,Data!$D$2:$D$2379,"Wool") -> 1880 | F5: =SUMIFS(Data!$L$2:$L$2379,Data!$N$2:$N$2379,$A5) -> 29444 | G5: =C5/B5 -> 59915 | H5: =C5/$C$7 -> 0.098269963 | I5: =E5/C5 -> 0.015688893
A6: Winter | B6: 4 | C6: =SUMIFS(Data!$J$2:$J$2379,Data!$N$2:$N$2379,$A6) -> 293366 | D6: =SUMIFS(Data!$J$2:$J$2379,Data!$N$2:$N$2379,$A6,Data!$D$2:$D$2379,"Bangles") -> 81420 | E6: =SUMIFS(Data!$J$2:$J$2379,Data!$N$2:$N$2379,$A6,Data!$D$2:$D$2379,"Wool") -> 211946 | F6: =SUMIFS(Data!$L$2:$L$2379,Data!$N$2:$N$2379,$A6) -> 51853 | G6: =C6/B6 -> 73341.5 | H6: =C6/$C$7 -> 0.24058304 | I6: =E6/C6 -> 0.72246273
A7: Total | B7: =SUM(B2:B6) -> 12 | C7: =SUM(C2:C6) -> 1219396 | D7: =SUM(D2:D6) -> 897620 | E7: =SUM(E2:E6) -> 321776 | F7: =SUM(F2:F6) -> 265562 | G7: =C7/B7 -> 101616.33 | H7: =SUM(H2:H6) -> 1 | I7: =E7/C7 -> 0.26388146
A9: Season mapping used in the source data: Winter = Nov-Feb, Spring = Mar-Apr, Summer = May-Jun, Monsoon = Jul-Sep, Autumn/Festive = Oct.

Sheet Products
A1: Product performance and ABC classification (by revenue)
A2: ABC: A cutoff (cumulative revenue share) | B2: 0.8
A3: ABC: B cutoff (cumulative revenue share) | B3: 0.95
A5: Product type | B5: Category | C5: Unit | D5: Revenue (Rs) | E5: Quantity | F5: Gross profit (Rs) | G5: Gross margin | H5: Revenue share | I5: Gross profit share | J5: Cumulative revenue share | K5: ABC class
A6: Bangles Box | B6: Bangles | C6: Box | D6: =SUMIFS(Data!$J$2:$J$2379,Data!$E$2:$E$2379,$A6) -> 618150 | E6: =SUMIFS(Data!$F$2:$F$2379,Data!$E$2:$E$2379,$A6) -> 4755 | F6: =SUMIFS(Data!$L$2:$L$2379,Data!$E$2:$E$2379,$A6) -> 142650 | G6: =F6/D6 -> 0.23076923 | H6: =D6/$D$17 -> 0.5069313 | I6: =F6/$F$17 -> 0.5371627 | J6: =SUM($H$6:H6) -> 0.5069313 | K6: =IF(J6<=$B$2,"A",IF(J6<=$B$3,"B","C")) -> A
A7: Wool Ball(q2) | B7: Wool | C7: Yarn | D7: =SUMIFS(Data!$J$2:$J$2379,Data!$E$2:$E$2379,$A7) -> 140140 | E7: =SUMIFS(Data!$F$2:$F$2379,Data!$E$2:$E$2379,$A7) -> 500.5 | F7: =SUMIFS(Data!$L$2:$L$2379,Data!$E$2:$E$2379,$A7) -> 20020 | G7: =F7/D7 -> 0.14285714 | H7: =D7/$D$17 -> 0.11492575 | I7: =F7/$F$17 -> 0.075387292 | J7: =SUM($H$6:H7) -> 0.62185705 | K7: =IF(J7<=$B$2,"A",IF(J7<=$B$3,"B","C")) -> A
A8: Wool Ball(q1) | B8: Wool | C8: Yarn | D8: =SUMIFS(Data!$J$2:$J$2379,Data!$E$2:$E$2379,$A8) -> 107640 | E8: =SUMIFS(Data!$F$2:$F$2379,Data!$E$2:$E$2379,$A8) -> 414 | F8: =SUMIFS(Data!$L$2:$L$2379,Data!$E$2:$E$2379,$A8) -> 16560 | G8: =F8/D8 -> 0.15384615 | H8: =D8/$D$17 -> 0.088273211 | I8: =F8/$F$17 -> 0.062358319 | J8: =SUM($H$6:H8) -> 0.71013026 | K8: =IF(J8<=$B$2,"A",IF(J8<=$B$3,"B","C")) -> A
A9: Bangles Set | B9: Bangles | C9: Box | D9: =SUMIFS(Data!$J$2:$J$2379,Data!$E$2:$E$2379,$A9) -> 102250 | E9: =SUMIFS(Data!$F$2:$F$2379,Data!$E$2:$E$2379,$A9) -> 409 | F9: =SUMIFS(Data!$L$2:$L$2379,Data!$E$2:$E$2379,$A9) -> 28630 | G9: =F9/D9 -> 0.28 | H9: =D9/$D$17 -> 0.08385299 | I9: =F9/$F$17 -> 0.1078091 | J9: =SUM($H$6:H9) -> 0.79398325 | K9: =IF(J9<=$B$2,"A",IF(J9<=$B$3,"B","C")) -> A
A10: Fancy Bangles Box | B10: Bangles | C10: Box | D10: =SUMIFS(Data!$J$2:$J$2379,Data!$E$2:$E$2379,$A10) -> 79500 | E10: =SUMIFS(Data!$F$2:$F$2379,Data!$E$2:$E$2379,$A10) -> 2650 | F10: =SUMIFS(Data!$L$2:$L$2379,Data!$E$2:$E$2379,$A10) -> 10600 | G10: =F10/D10 -> 0.13333333 | H10: =D10/$D$17 -> 0.065196212 | I10: =F10/$F$17 -> 0.039915349 | J10: =SUM($H$6:H10) -> 0.85917946 | K10: =IF(J10<=$B$2,"A",IF(J10<=$B$3,"B","C")) -> B
A11: Bangles Box (Plus size) | B11: Bangles | C11: Box | D11: =SUMIFS(Data!$J$2:$J$2379,Data!$E$2:$E$2379,$A11) -> 69600 | E11: =SUMIFS(Data!$F$2:$F$2379,Data!$E$2:$E$2379,$A11) -> 464 | F11: =SUMIFS(Data!$L$2:$L$2379,Data!$E$2:$E$2379,$A11) -> 23200 | G11: =F11/D11 -> 0.33333333 | H11: =D11/$D$17 -> 0.057077438 | I11: =F11/$F$17 -> 0.087361897 | J11: =SUM($H$6:H11) -> 0.9162569 | K11: =IF(J11<=$B$2,"A",IF(J11<=$B$3,"B","C")) -> B
A12: Wool Ball Packet | B12: Wool | C12: Packet | D12: =SUMIFS(Data!$J$2:$J$2379,Data!$E$2:$E$2379,$A12) -> 48600 | E12: =SUMIFS(Data!$F$2:$F$2379,Data!$E$2:$E$2379,$A12) -> 162 | F12: =SUMIFS(Data!$L$2:$L$2379,Data!$E$2:$E$2379,$A12) -> 5670 | G12: =F12/D12 -> 0.11666667 | H12: =D12/$D$17 -> 0.039855797 | I12: =F12/$F$17 -> 0.021350946 | J12: =SUM($H$6:H12) -> 0.9561127 | K12: =IF(J12<=$B$2,"A",IF(J12<=$B$3,"B","C")) -> C
A13: Metal Bangles | B13: Bangles | C13: Box | D13: =SUMIFS(Data!$J$2:$J$2379,Data!$E$2:$E$2379,$A13) -> 28120 | E13: =SUMIFS(Data!$F$2:$F$2379,Data!$E$2:$E$2379,$A13) -> 296 | F13: =SUMIFS(Data!$L$2:$L$2379,Data!$E$2:$E$2379,$A13) -> 11840 | G13: =F13/D13 -> 0.42105263 | H13: =D13/$D$17 -> 0.023060597 | I13: =F13/$F$17 -> 0.044584692 | J13: =SUM($H$6:H13) -> 0.9791733 | K13: =IF(J13<=$B$2,"A",IF(J13<=$B$3,"B","C")) -> C
A14: Baby Soft Wool | B14: Wool | C14: Jar | D14: =SUMIFS(Data!$J$2:$J$2379,Data!$E$2:$E$2379,$A14) -> 15550 | E14: =SUMIFS(Data!$F$2:$F$2379,Data!$E$2:$E$2379,$A14) -> 77.75 | F14: =SUMIFS(Data!$L$2:$L$2379,Data!$E$2:$E$2379,$A14) -> 3110 | G14: =F14/D14 -> 0.2 | H14: =D14/$D$17 -> 0.012752215 | I14: =F14/$F$17 -> 0.011711013 | J14: =SUM($H$6:H14) -> 0.99192551 | K14: =IF(J14<=$B$2,"A",IF(J14<=$B$3,"B","C")) -> C
A15: Button | B15: Wool | C15: Pieces | D15: =SUMIFS(Data!$J$2:$J$2379,Data!$E$2:$E$2379,$A15) -> 5376 | E15: =SUMIFS(Data!$F$2:$F$2379,Data!$E$2:$E$2379,$A15) -> 896 | F15: =SUMIFS(Data!$L$2:$L$2379,Data!$E$2:$E$2379,$A15) -> 1792 | G15: =F15/D15 -> 0.33333333 | H15: =D15/$D$17 -> 0.0044087401 | I15: =F15/$F$17 -> 0.0067479534 | J15: =SUM($H$6:H15) -> 0.99633425 | K15: =IF(J15<=$B$2,"A",IF(J15<=$B$3,"B","C")) -> C
A16: Knitting Needle (Pair) | B16: Wool | C16: Pieces | D16: =SUMIFS(Data!$J$2:$J$2379,Data!$E$2:$E$2379,$A16) -> 4470 | E16: =SUMIFS(Data!$F$2:$F$2379,Data!$E$2:$E$2379,$A16) -> 149 | F16: =SUMIFS(Data!$L$2:$L$2379,Data!$E$2:$E$2379,$A16) -> 1490 | G16: =F16/D16 -> 0.33333333 | H16: =D16/$D$17 -> 0.0036657493 | I16: =F16/$F$17 -> 0.0056107425 | J16: =SUM($H$6:H16) -> 1 | K16: =IF(J16<=$B$2,"A",IF(J16<=$B$3,"B","C")) -> C
A17: Total | D17: =SUM(D6:D16) -> 1219396 | F17: =SUM(F6:F16) -> 265562 | G17: =F17/D17 -> 0.21778159 | H17: =SUM(H6:H16) -> 1 | I17: =SUM(I6:I16) -> 1
A19: Revenue share and gross-profit share differ: e.g. Bangles Box = ~50.7% of revenue but ~53.7% of gross profit. Quote them separately.

Sheet ABC-XYZ
A1: ABC-XYZ inventory classification
A2: XYZ: X if CV <= | B2: 0.5
A3: XYZ: Y if CV <= (else Z) | B3: 1
A5: Product type | B5: ABC | C5: Feb | D5: Mar | E5: Apr | F5: May | G5: Jun | H5: Jul | I5: Aug | J5: Sep | K5: Oct | L5: Nov | M5: Dec | N5: Jan | O5: Mean monthly qty | P5: Std dev | Q5: CV | R5: XYZ | S5: Class | T5: Suggested stocking policy
A6: Bangles Box | B6: =INDEX(Products!$K$6:$K$16,MATCH($A6,Products!$A$6:$A$16,0)) -> A | C6: =SUMIFS(Data!$F$2:$F$2379,Data!$E$2:$E$2379,$A6,Data!$C$2:$C$2379,"February") -> 131 | D6: =SUMIFS(Data!$F$2:$F$2379,Data!$E$2:$E$2379,$A6,Data!$C$2:$C$2379,"March") -> 201 | E6: =SUMIFS(Data!$F$2:$F$2379,Data!$E$2:$E$2379,$A6,Data!$C$2:$C$2379,"April") -> 352 | F6: =SUMIFS(Data!$F$2:$F$2379,Data!$E$2:$E$2379,$A6,Data!$C$2:$C$2379,"May") -> 311 | G6: =SUMIFS(Data!$F$2:$F$2379,Data!$E$2:$E$2379,$A6,Data!$C$2:$C$2379,"June") -> 362 | H6: =SUMIFS(Data!$F$2:$F$2379,Data!$E$2:$E$2379,$A6,Data!$C$2:$C$2379,"July") -> 1023 | I6: =SUMIFS(Data!$F$2:$F$2379,Data!$E$2:$E$2379,$A6,Data!$C$2:$C$2379,"August") -> 363 | J6: =SUMIFS(Data!$F$2:$F$2379,Data!$E$2:$E$2379,$A6,Data!$C$2:$C$2379,"September") -> 78 | K6: =SUMIFS(Data!$F$2:$F$2379,Data!$E$2:$E$2379,$A6,Data!$C$2:$C$2379,"October") -> 1568 | L6: =SUMIFS(Data!$F$2:$F$2379,Data!$E$2:$E$2379,$A6,Data!$C$2:$C$2379,"November") -> 80 | M6: =SUMIFS(Data!$F$2:$F$2379,Data!$E$2:$E$2379,$A6,Data!$C$2:$C$2379,"December") -> 112 | N6: =SUMIFS(Data!$F$2:$F$2379,Data!$E$2:$E$2379,$A6,Data!$C$2:$C$2379,"January") -> 174 | O6: =AVERAGE(C6:N6) -> 396.25 | P6: =STDEVP(C6:N6) -> 429.85349 | Q6: =P6/O6 -> 1.0848038 | R6: =IF(Q6<=$B$2,"X",IF(Q6<=$B$3,"Y","Z")) -> Z | S6: =B6&R6 -> AZ | T6: =IF(B6="A",IF(R6="X","Keep in stock all year",IF(R6="Y","Keep a seasonal buffer; review monthly","Stock ahead of its peak months; pre-book with wholesalers")),IF(B6="B","Order in smaller lots ahead of season; reorder as it sells","Order on demand; do not hold surplus")) -> Stock ahead of its peak months; pre-book with wholesalers
A7: Wool Ball(q2) | B7: =INDEX(Products!$K$6:$K$16,MATCH($A7,Products!$A$6:$A$16,0)) -> A | C7: =SUMIFS(Data!$F$2:$F$2379,Data!$E$2:$E$2379,$A7,Data!$C$2:$C$2379,"February") -> 117.5 | D7: =SUMIFS(Data!$F$2:$F$2379,Data!$E$2:$E$2379,$A7,Data!$C$2:$C$2379,"March") -> 118.5 | E7: =SUMIFS(Data!$F$2:$F$2379,Data!$E$2:$E$2379,$A7,Data!$C$2:$C$2379,"April") -> 26.5 | F7: =SUMIFS(Data!$F$2:$F$2379,Data!$E$2:$E$2379,$A7,Data!$C$2:$C$2379,"May") -> 1 | G7: =SUMIFS(Data!$F$2:$F$2379,Data!$E$2:$E$2379,$A7,Data!$C$2:$C$2379,"June") -> 0 | H7: =SUMIFS(Data!$F$2:$F$2379,Data!$E$2:$E$2379,$A7,Data!$C$2:$C$2379,"July") -> 2 | I7: =SUMIFS(Data!$F$2:$F$2379,Data!$E$2:$E$2379,$A7,Data!$C$2:$C$2379,"August") -> 0 | J7: =SUMIFS(Data!$F$2:$F$2379,Data!$E$2:$E$2379,$A7,Data!$C$2:$C$2379,"September") -> 7 | K7: =SUMIFS(Data!$F$2:$F$2379,Data!$E$2:$E$2379,$A7,Data!$C$2:$C$2379,"October") -> 47.5 | L7: =SUMIFS(Data!$F$2:$F$2379,Data!$E$2:$E$2379,$A7,Data!$C$2:$C$2379,"November") -> 38.75 | M7: =SUMIFS(Data!$F$2:$F$2379,Data!$E$2:$E$2379,$A7,Data!$C$2:$C$2379,"December") -> 72.75 | N7: =SUMIFS(Data!$F$2:$F$2379,Data!$E$2:$E$2379,$A7,Data!$C$2:$C$2379,"January") -> 69 | O7: =AVERAGE(C7:N7) -> 41.708333 | P7: =STDEVP(C7:N7) -> 42.368526 | Q7: =P7/O7 -> 1.0158288 | R7: =IF(Q7<=$B$2,"X",IF(Q7<=$B$3,"Y","Z")) -> Z | S7: =B7&R7 -> AZ | T7: =IF(B7="A",IF(R7="X","Keep in stock all year",IF(R7="Y","Keep a seasonal buffer; review monthly","Stock ahead of its peak months; pre-book with wholesalers")),IF(B7="B","Order in smaller lots ahead of season; reorder as it sells","Order on demand; do not hold surplus")) -> Stock ahead of its peak months; pre-book with wholesalers
A8: Wool Ball(q1) | B8: =INDEX(Products!$K$6:$K$16,MATCH($A8,Products!$A$6:$A$16,0)) -> A | C8: =SUMIFS(Data!$F$2:$F$2379,Data!$E$2:$E$2379,$A8,Data!$C$2:$C$2379,"February") -> 75 | D8: =SUMIFS(Data!$F$2:$F$2379,Data!$E$2:$E$2379,$A8,Data!$C$2:$C$2379,"March") -> 61.5 | E8: =SUMIFS(Data!$F$2:$F$2379,Data!$E$2:$E$2379,$A8,Data!$C$2:$C$2379,"April") -> 15.5 | F8: =SUMIFS(Data!$F$2:$F$2379,Data!$E$2:$E$2379,$A8,Data!$C$2:$C$2379,"May") -> 0 | G8: =SUMIFS(Data!$F$2:$F$2379,Data!$E$2:$E$2379,$A8,Data!$C$2:$C$2379,"June") -> 0 | H8: =SUMIFS(Data!$F$2:$F$2379,Data!$E$2:$E$2379,$A8,Data!$C$2:$C$2379,"July") -> 2.5 | I8: =SUMIFS(Data!$F$2:$F$2379,Data!$E$2:$E$2379,$A8,Data!$C$2:$C$2379,"August") -> 0 | J8: =SUMIFS(Data!$F$2:$F$2379,Data!$E$2:$E$2379,$A8,Data!$C$2:$C$2379,"September") -> 7.5 | K8: =SUMIFS(Data!$F$2:$F$2379,Data!$E$2:$E$2379,$A8,Data!$C$2:$C$2379,"October") -> 27 | L8: =SUMIFS(Data!$F$2:$F$2379,Data!$E$2:$E$2379,$A8,Data!$C$2:$C$2379,"November") -> 57 | M8: =SUMIFS(Data!$F$2:$F$2379,Data!$E$2:$E$2379,$A8,Data!$C$2:$C$2379,"December") -> 72.5 | N8: =SUMIFS(Data!$F$2:$F$2379,Data!$E$2:$E$2379,$A8,Data!$C$2:$C$2379,"January") -> 95.5 | O8: =AVERAGE(C8:N8) -> 34.5 | P8: =STDEVP(C8:N8) -> 33.888912 | Q8: =P8/O8 -> 0.98228729 | R8: =IF(Q8<=$B$2,"X",IF(Q8<=$B$3,"Y","Z")) -> Y | S8: =B8&R8 -> AY | T8: =IF(B8="A",IF(R8="X","Keep in stock all year",IF(R8="Y","Keep a seasonal buffer; review monthly","Stock ahead of its peak months; pre-book with wholesalers")),IF(B8="B","Order in smaller lots ahead of season; reorder as it sells","Order on demand; do not hold surplus")) -> Keep a seasonal buffer; review monthly
A9: Bangles Set | B9: =INDEX(Products!$K$6:$K$16,MATCH($A9,Products!$A$6:$A$16,0)) -> A | C9: =SUMIFS(Data!$F$2:$F$2379,Data!$E$2:$E$2379,$A9,Data!$C$2:$C$2379,"February") -> 0 | D9: =SUMIFS(Data!$F$2:$F$2379,Data!$E$2:$E$2379,$A9,Data!$C$2:$C$2379,"March") -> 0 | E9: =SUMIFS(Data!$F$2:$F$2379,Data!$E$2:$E$2379,$A9,Data!$C$2:$C$2379,"April") -> 4 | F9: =SUMIFS(Data!$F$2:$F$2379,Data!$E$2:$E$2379,$A9,Data!$C$2:$C$2379,"May") -> 27 | G9: =SUMIFS(Data!$F$2:$F$2379,Data!$E$2:$E$2379,$A9,Data!$C$2:$C$2379,"June") -> 15 | H9: =SUMIFS(Data!$F$2:$F$2379,Data!$E$2:$E$2379,$A9,Data!$C$2:$C$2379,"July") -> 111 | I9: =SUMIFS(Data!$F$2:$F$2379,Data!$E$2:$E$2379,$A9,Data!$C$2:$C$2379,"August") -> 61 | J9: =SUMIFS(Data!$F$2:$F$2379,Data!$E$2:$E$2379,$A9,Data!$C$2:$C$2379,"September") -> 19 | K9: =SUMIFS(Data!$F$2:$F$2379,Data!$E$2:$E$2379,$A9,Data!$C$2:$C$2379,"October") -> 172 | L9: =SUMIFS(Data!$F$2:$F$2379,Data!$E$2:$E$2379,$A9,Data!$C$2:$C$2379,"November") -> 0 | M9: =SUMIFS(Data!$F$2:$F$2379,Data!$E$2:$E$2379,$A9,Data!$C$2:$C$2379,"December") -> 0 | N9: =SUMIFS(Data!$F$2:$F$2379,Data!$E$2:$E$2379,$A9,Data!$C$2:$C$2379,"January") -> 0 | O9: =AVERAGE(C9:N9) -> 34.083333 | P9: =STDEVP(C9:N9) -> 52.453882 | Q9: =P9/O9 -> 1.5389892 | R9: =IF(Q9<=$B$2,"X",IF(Q9<=$B$3,"Y","Z")) -> Z | S9: =B9&R9 -> AZ | T9: =IF(B9="A",IF(R9="X","Keep in stock all year",IF(R9="Y","Keep a seasonal buffer; review monthly","Stock ahead of its peak months; pre-book with wholesalers")),IF(B9="B","Order in smaller lots ahead of season; reorder as it sells","Order on demand; do not hold surplus")) -> Stock ahead of its peak months; pre-book with wholesalers
A10: Fancy Bangles Box | B10: =INDEX(Products!$K$6:$K$16,MATCH($A10,Products!$A$6:$A$16,0)) -> B | C10: =SUMIFS(Data!$F$2:$F$2379,Data!$E$2:$E$2379,$A10,Data!$C$2:$C$2379,"February") -> 2 | D10: =SUMIFS(Data!$F$2:$F$2379,Data!$E$2:$E$2379,$A10,Data!$C$2:$C$2379,"March") -> 82 | E10: =SUMIFS(Data!$F$2:$F$2379,Data!$E$2:$E$2379,$A10,Data!$C$2:$C$2379,"April") -> 170 | F10: =SUMIFS(Data!$F$2:$F$2379,Data!$E$2:$E$2379,$A10,Data!$C$2:$C$2379,"May") -> 103 | G10: =SUMIFS(Data!$F$2:$F$2379,Data!$E$2:$E$2379,$A10,Data!$C$2:$C$2379,"June") -> 58 | H10: =SUMIFS(Data!$F$2:$F$2379,Data!$E$2:$E$2379,$A10,Data!$C$2:$C$2379,"July") -> 605 | I10: =SUMIFS(Data!$F$2:$F$2379,Data!$E$2:$E$2379,$A10,Data!$C$2:$C$2379,"August") -> 382 | J10: =SUMIFS(Data!$F$2:$F$2379,Data!$E$2:$E$2379,$A10,Data!$C$2:$C$2379,"September") -> 106 | K10: =SUMIFS(Data!$F$2:$F$2379,Data!$E$2:$E$2379,$A10,Data!$C$2:$C$2379,"October") -> 995 | L10: =SUMIFS(Data!$F$2:$F$2379,Data!$E$2:$E$2379,$A10,Data!$C$2:$C$2379,"November") -> 66 | M10: =SUMIFS(Data!$F$2:$F$2379,Data!$E$2:$E$2379,$A10,Data!$C$2:$C$2379,"December") -> 44 | N10: =SUMIFS(Data!$F$2:$F$2379,Data!$E$2:$E$2379,$A10,Data!$C$2:$C$2379,"January") -> 37 | O10: =AVERAGE(C10:N10) -> 220.83333 | P10: =STDEVP(C10:N10) -> 286.54023 | Q10: =P10/O10 -> 1.2975407 | R10: =IF(Q10<=$B$2,"X",IF(Q10<=$B$3,"Y","Z")) -> Z | S10: =B10&R10 -> BZ | T10: =IF(B10="A",IF(R10="X","Keep in stock all year",IF(R10="Y","Keep a seasonal buffer; review monthly","Stock ahead of its peak months; pre-book with wholesalers")),IF(B10="B","Order in smaller lots ahead of season; reorder as it sells","Order on demand; do not hold surplus")) -> Order in smaller lots ahead of season; reorder as it sells
A11: Bangles Box (Plus size) | B11: =INDEX(Products!$K$6:$K$16,MATCH($A11,Products!$A$6:$A$16,0)) -> B | C11: =SUMIFS(Data!$F$2:$F$2379,Data!$E$2:$E$2379,$A11,Data!$C$2:$C$2379,"February") -> 39 | D11: =SUMIFS(Data!$F$2:$F$2379,Data!$E$2:$E$2379,$A11,Data!$C$2:$C$2379,"March") -> 31 | E11: =SUMIFS(Data!$F$2:$F$2379,Data!$E$2:$E$2379,$A11,Data!$C$2:$C$2379,"April") -> 35 | F11: =SUMIFS(Data!$F$2:$F$2379,Data!$E$2:$E$2379,$A11,Data!$C$2:$C$2379,"May") -> 31 | G11: =SUMIFS(Data!$F$2:$F$2379,Data!$E$2:$E$2379,$A11,Data!$C$2:$C$2379,"June") -> 42 | H11: =SUMIFS(Data!$F$2:$F$2379,Data!$E$2:$E$2379,$A11,Data!$C$2:$C$2379,"July") -> 159 | I11: =SUMIFS(Data!$F$2:$F$2379,Data!$E$2:$E$2379,$A11,Data!$C$2:$C$2379,"August") -> 85 | J11: =SUMIFS(Data!$F$2:$F$2379,Data!$E$2:$E$2379,$A11,Data!$C$2:$C$2379,"September") -> 0 | K11: =SUMIFS(Data!$F$2:$F$2379,Data!$E$2:$E$2379,$A11,Data!$C$2:$C$2379,"October") -> 0 | L11: =SUMIFS(Data!$F$2:$F$2379,Data!$E$2:$E$2379,$A11,Data!$C$2:$C$2379,"November") -> 32 | M11: =SUMIFS(Data!$F$2:$F$2379,Data!$E$2:$E$2379,$A11,Data!$C$2:$C$2379,"December") -> 5 | N11: =SUMIFS(Data!$F$2:$F$2379,Data!$E$2:$E$2379,$A11,Data!$C$2:$C$2379,"January") -> 5 | O11: =AVERAGE(C11:N11) -> 38.666667 | P11: =STDEVP(C11:N11) -> 42.886154 | Q11: =P11/O11 -> 1.1091247 | R11: =IF(Q11<=$B$2,"X",IF(Q11<=$B$3,"Y","Z")) -> Z | S11: =B11&R11 -> BZ | T11: =IF(B11="A",IF(R11="X","Keep in stock all year",IF(R11="Y","Keep a seasonal buffer; review monthly","Stock ahead of its peak months; pre-book with wholesalers")),IF(B11="B","Order in smaller lots ahead of season; reorder as it sells","Order on demand; do not hold surplus")) -> Order in smaller lots ahead of season; reorder as it sells
A12: Wool Ball Packet | B12: =INDEX(Products!$K$6:$K$16,MATCH($A12,Products!$A$6:$A$16,0)) -> C | C12: =SUMIFS(Data!$F$2:$F$2379,Data!$E$2:$E$2379,$A12,Data!$C$2:$C$2379,"February") -> 14 | D12: =SUMIFS(Data!$F$2:$F$2379,Data!$E$2:$E$2379,$A12,Data!$C$2:$C$2379,"March") -> 18 | E12: =SUMIFS(Data!$F$2:$F$2379,Data!$E$2:$E$2379,$A12,Data!$C$2:$C$2379,"April") -> 8 | F12: =SUMIFS(Data!$F$2:$F$2379,Data!$E$2:$E$2379,$A12,Data!$C$2:$C$2379,"May") -> 2 | G12: =SUMIFS(Data!$F$2:$F$2379,Data!$E$2:$E$2379,$A12,Data!$C$2:$C$2379,"June") -> 2 | H12: =SUMIFS(Data!$F$2:$F$2379,Data!$E$2:$E$2379,$A12,Data!$C$2:$C$2379,"July") -> 1 | I12: =SUMIFS(Data!$F$2:$F$2379,Data!$E$2:$E$2379,$A12,Data!$C$2:$C$2379,"August") -> 1 | J12: =SUMIFS(Data!$F$2:$F$2379,Data!$E$2:$E$2379,$A12,Data!$C$2:$C$2379,"September") -> 3 | K12: =SUMIFS(Data!$F$2:$F$2379,Data!$E$2:$E$2379,$A12,Data!$C$2:$C$2379,"October") -> 14 | L12: =SUMIFS(Data!$F$2:$F$2379,Data!$E$2:$E$2379,$A12,Data!$C$2:$C$2379,"November") -> 24.5 | M12: =SUMIFS(Data!$F$2:$F$2379,Data!$E$2:$E$2379,$A12,Data!$C$2:$C$2379,"December") -> 39.5 | N12: =SUMIFS(Data!$F$2:$F$2379,Data!$E$2:$E$2379,$A12,Data!$C$2:$C$2379,"January") -> 35 | O12: =AVERAGE(C12:N12) -> 13.5 | P12: =STDEVP(C12:N12) -> 12.901873 | Q12: =P12/O12 -> 0.95569431 | R12: =IF(Q12<=$B$2,"X",IF(Q12<=$B$3,"Y","Z")) -> Y | S12: =B12&R12 -> CY | T12: =IF(B12="A",IF(R12="X","Keep in stock all year",IF(R12="Y","Keep a seasonal buffer; review monthly","Stock ahead of its peak months; pre-book with wholesalers")),IF(B12="B","Order in smaller lots ahead of season; reorder as it sells","Order on demand; do not hold surplus")) -> Order on demand; do not hold surplus
A13: Metal Bangles | B13: =INDEX(Products!$K$6:$K$16,MATCH($A13,Products!$A$6:$A$16,0)) -> C | C13: =SUMIFS(Data!$F$2:$F$2379,Data!$E$2:$E$2379,$A13,Data!$C$2:$C$2379,"February") -> 0 | D13: =SUMIFS(Data!$F$2:$F$2379,Data!$E$2:$E$2379,$A13,Data!$C$2:$C$2379,"March") -> 0 | E13: =SUMIFS(Data!$F$2:$F$2379,Data!$E$2:$E$2379,$A13,Data!$C$2:$C$2379,"April") -> 23 | F13: =SUMIFS(Data!$F$2:$F$2379,Data!$E$2:$E$2379,$A13,Data!$C$2:$C$2379,"May") -> 17 | G13: =SUMIFS(Data!$F$2:$F$2379,Data!$E$2:$E$2379,$A13,Data!$C$2:$C$2379,"June") -> 27 | H13: =SUMIFS(Data!$F$2:$F$2379,Data!$E$2:$E$2379,$A13,Data!$C$2:$C$2379,"July") -> 56 | I13: =SUMIFS(Data!$F$2:$F$2379,Data!$E$2:$E$2379,$A13,Data!$C$2:$C$2379,"August") -> 0 | J13: =SUMIFS(Data!$F$2:$F$2379,Data!$E$2:$E$2379,$A13,Data!$C$2:$C$2379,"September") -> 18 | K13: =SUMIFS(Data!$F$2:$F$2379,Data!$E$2:$E$2379,$A13,Data!$C$2:$C$2379,"October") -> 153 | L13: =SUMIFS(Data!$F$2:$F$2379,Data!$E$2:$E$2379,$A13,Data!$C$2:$C$2379,"November") -> 2 | M13: =SUMIFS(Data!$F$2:$F$2379,Data!$E$2:$E$2379,$A13,Data!$C$2:$C$2379,"December") -> 0 | N13: =SUMIFS(Data!$F$2:$F$2379,Data!$E$2:$E$2379,$A13,Data!$C$2:$C$2379,"January") -> 0 | O13: =AVERAGE(C13:N13) -> 24.666667 | P13: =STDEVP(C13:N13) -> 41.95103 | Q13: =P13/O13 -> 1.7007174 | R13: =IF(Q13<=$B$2,"X",IF(Q13<=$B$3,"Y","Z")) -> Z | S13: =B13&R13 -> CZ | T13: =IF(B13="A",IF(R13="X","Keep in stock all year",IF(R13="Y","Keep a seasonal buffer; review monthly","Stock ahead of its peak months; pre-book with wholesalers")),IF(B13="B","Order in smaller lots ahead of season; reorder as it sells","Order on demand; do not hold surplus")) -> Order on demand; do not hold surplus
A14: Baby Soft Wool | B14: =INDEX(Products!$K$6:$K$16,MATCH($A14,Products!$A$6:$A$16,0)) -> C | C14: =SUMIFS(Data!$F$2:$F$2379,Data!$E$2:$E$2379,$A14,Data!$C$2:$C$2379,"February") -> 14 | D14: =SUMIFS(Data!$F$2:$F$2379,Data!$E$2:$E$2379,$A14,Data!$C$2:$C$2379,"March") -> 9 | E14: =SUMIFS(Data!$F$2:$F$2379,Data!$E$2:$E$2379,$A14,Data!$C$2:$C$2379,"April") -> 2 | F14: =SUMIFS(Data!$F$2:$F$2379,Data!$E$2:$E$2379,$A14,Data!$C$2:$C$2379,"May") -> 0 | G14: =SUMIFS(Data!$F$2:$F$2379,Data!$E$2:$E$2379,$A14,Data!$C$2:$C$2379,"June") -> 2 | H14: =SUMIFS(Data!$F$2:$F$2379,Data!$E$2:$E$2379,$A14,Data!$C$2:$C$2379,"July") -> 0 | I14: =SUMIFS(Data!$F$2:$F$2379,Data!$E$2:$E$2379,$A14,Data!$C$2:$C$2379,"August") -> 0 | J14: =SUMIFS(Data!$F$2:$F$2379,Data!$E$2:$E$2379,$A14,Data!$C$2:$C$2379,"September") -> 2 | K14: =SUMIFS(Data!$F$2:$F$2379,Data!$E$2:$E$2379,$A14,Data!$C$2:$C$2379,"October") -> 18 | L14: =SUMIFS(Data!$F$2:$F$2379,Data!$E$2:$E$2379,$A14,Data!$C$2:$C$2379,"November") -> 13.75 | M14: =SUMIFS(Data!$F$2:$F$2379,Data!$E$2:$E$2379,$A14,Data!$C$2:$C$2379,"December") -> 9 | N14: =SUMIFS(Data!$F$2:$F$2379,Data!$E$2:$E$2379,$A14,Data!$C$2:$C$2379,"January") -> 8 | O14: =AVERAGE(C14:N14) -> 6.4791667 | P14: =STDEVP(C14:N14) -> 6.0780157 | Q14: =P14/O14 -> 0.93808602 | R14: =IF(Q14<=$B$2,"X",IF(Q14<=$B$3,"Y","Z")) -> Y | S14: =B14&R14 -> CY | T14: =IF(B14="A",IF(R14="X","Keep in stock all year",IF(R14="Y","Keep a seasonal buffer; review monthly","Stock ahead of its peak months; pre-book with wholesalers")),IF(B14="B","Order in smaller lots ahead of season; reorder as it sells","Order on demand; do not hold surplus")) -> Order on demand; do not hold surplus
A15: Button | B15: =INDEX(Products!$K$6:$K$16,MATCH($A15,Products!$A$6:$A$16,0)) -> C | C15: =SUMIFS(Data!$F$2:$F$2379,Data!$E$2:$E$2379,$A15,Data!$C$2:$C$2379,"February") -> 61 | D15: =SUMIFS(Data!$F$2:$F$2379,Data!$E$2:$E$2379,$A15,Data!$C$2:$C$2379,"March") -> 98 | E15: =SUMIFS(Data!$F$2:$F$2379,Data!$E$2:$E$2379,$A15,Data!$C$2:$C$2379,"April") -> 0 | F15: =SUMIFS(Data!$F$2:$F$2379,Data!$E$2:$E$2379,$A15,Data!$C$2:$C$2379,"May") -> 0 | G15: =SUMIFS(Data!$F$2:$F$2379,Data!$E$2:$E$2379,$A15,Data!$C$2:$C$2379,"June") -> 0 | H15: =SUMIFS(Data!$F$2:$F$2379,Data!$E$2:$E$2379,$A15,Data!$C$2:$C$2379,"July") -> 0 | I15: =SUMIFS(Data!$F$2:$F$2379,Data!$E$2:$E$2379,$A15,Data!$C$2:$C$2379,"August") -> 0 | J15: =SUMIFS(Data!$F$2:$F$2379,Data!$E$2:$E$2379,$A15,Data!$C$2:$C$2379,"September") -> 0 | K15: =SUMIFS(Data!$F$2:$F$2379,Data!$E$2:$E$2379,$A15,Data!$C$2:$C$2379,"October") -> 32 | L15: =SUMIFS(Data!$F$2:$F$2379,Data!$E$2:$E$2379,$A15,Data!$C$2:$C$2379,"November") -> 163 | M15: =SUMIFS(Data!$F$2:$F$2379,Data!$E$2:$E$2379,$A15,Data!$C$2:$C$2379,"December") -> 277 | N15: =SUMIFS(Data!$F$2:$F$2379,Data!$E$2:$E$2379,$A15,Data!$C$2:$C$2379,"January") -> 265 | O15: =AVERAGE(C15:N15) -> 74.666667 | P15: =STDEVP(C15:N15) -> 100.40363 | Q15: =P15/O15 -> 1.3446915 | R15: =IF(Q15<=$B$2,"X",IF(Q15<=$B$3,"Y","Z")) -> Z | S15: =B15&R15 -> CZ | T15: =IF(B15="A",IF(R15="X","Keep in stock all year",IF(R15="Y","Keep a seasonal buffer; review monthly","Stock ahead of its peak months; pre-book with wholesalers")),IF(B15="B","Order in smaller lots ahead of season; reorder as it sells","Order on demand; do not hold surplus")) -> Order on demand; do not hold surplus
A16: Knitting Needle (Pair) | B16: =INDEX(Products!$K$6:$K$16,MATCH($A16,Products!$A$6:$A$16,0)) -> C | C16: =SUMIFS(Data!$F$2:$F$2379,Data!$E$2:$E$2379,$A16,Data!$C$2:$C$2379,"February") -> 23 | D16: =SUMIFS(Data!$F$2:$F$2379,Data!$E$2:$E$2379,$A16,Data!$C$2:$C$2379,"March") -> 28 | E16: =SUMIFS(Data!$F$2:$F$2379,Data!$E$2:$E$2379,$A16,Data!$C$2:$C$2379,"April") -> 7 | F16: =SUMIFS(Data!$F$2:$F$2379,Data!$E$2:$E$2379,$A16,Data!$C$2:$C$2379,"May") -> 0 | G16: =SUMIFS(Data!$F$2:$F$2379,Data!$E$2:$E$2379,$A16,Data!$C$2:$C$2379,"June") -> 0 | H16: =SUMIFS(Data!$F$2:$F$2379,Data!$E$2:$E$2379,$A16,Data!$C$2:$C$2379,"July") -> 0 | I16: =SUMIFS(Data!$F$2:$F$2379,Data!$E$2:$E$2379,$A16,Data!$C$2:$C$2379,"August") -> 0 | J16: =SUMIFS(Data!$F$2:$F$2379,Data!$E$2:$E$2379,$A16,Data!$C$2:$C$2379,"September") -> 0 | K16: =SUMIFS(Data!$F$2:$F$2379,Data!$E$2:$E$2379,$A16,Data!$C$2:$C$2379,"October") -> 12 | L16: =SUMIFS(Data!$F$2:$F$2379,Data!$E$2:$E$2379,$A16,Data!$C$2:$C$2379,"November") -> 32 | M16: =SUMIFS(Data!$F$2:$F$2379,Data!$E$2:$E$2379,$A16,Data!$C$2:$C$2379,"December") -> 19 | N16: =SUMIFS(Data!$F$2:$F$2379,Data!$E$2:$E$2379,$A16,Data!$C$2:$C$2379,"January") -> 28 | O16: =AVERAGE(C16:N16) -> 12.416667 | P16: =STDEVP(C16:N16) -> 12.331926 | Q16: =P16/O16 -> 0.99317522 | R16: =IF(Q16<=$B$2,"X",IF(Q16<=$B$3,"Y","Z")) -> Y | S16: =B16&R16 -> CY | T16: =IF(B16="A",IF(R16="X","Keep in stock all year",IF(R16="Y","Keep a seasonal buffer; review monthly","Stock ahead of its peak months; pre-book with wholesalers")),IF(B16="B","Order in smaller lots ahead of season; reorder as it sells","Order on demand; do not hold surplus")) -> Order on demand; do not hold surplus
A18: CV = standard deviation / mean of monthly units (12 months, Feb 2024 - Jan 2025). Lower CV = steadier demand.
A19: Finding: no product has stable (X) demand; CV values near the 1.0 cutoff (e.g. 0.94-1.02) are borderline, so treat Y/Z as a spectrum rather than a hard line.

Sheet Pareto
A1: Rank | B1: Revenue (Rs) | C1: Cumulative (Rs) | D1: Cumulative share
A2: 1 | B2: =LARGE(Data!$J$2:$J$2379,A2) -> 3250 | C2: =B2 -> 3250 | D2: =C2/SUM(Data!$J$2:$J$2379) -> 0.0026652539
A3: 2 | B3: =LARGE(Data!$J$2:$J$2379,A3) -> 3120 | C3: =C2+B3 -> 6370 | D3: =C3/SUM(Data!$J$2:$J$2379) -> 0.0052238977
A4: 3 | B4: =LARGE(Data!$J$2:$J$2379,A4) -> 3000 | C4: =C3+B4 -> 9370 | D4: =C4/SUM(Data!$J$2:$J$2379) -> 0.0076841321
A5: 4 | B5: =LARGE(Data!$J$2:$J$2379,A5) -> 2600 | C5: =C4+B5 -> 11970 | D5: =C5/SUM(Data!$J$2:$J$2379) -> 0.0098163353
A6: 5 | B6: =LARGE(Data!$J$2:$J$2379,A6) -> 2600 | C6: =C5+B6 -> 14570 | D6: =C6/SUM(Data!$J$2:$J$2379) -> 0.011948538
A7: 6 | B7: =LARGE(Data!$J$2:$J$2379,A7) -> 2600 | C7: =C6+B7 -> 17170 | D7: =C7/SUM(Data!$J$2:$J$2379) -> 0.014080742
A8: 7 | B8: =LARGE(Data!$J$2:$J$2379,A8) -> 2500 | C8: =C7+B8 -> 19670 | D8: =C8/SUM(Data!$J$2:$J$2379) -> 0.016130937
A9: 8 | B9: =LARGE(Data!$J$2:$J$2379,A9) -> 2340 | C9: =C8+B9 -> 22010 | D9: =C9/SUM(Data!$J$2:$J$2379) -> 0.01804992
A10: 9 | B10: =LARGE(Data!$J$2:$J$2379,A10) -> 2340 | C10: =C9+B10 -> 24350 | D10: =C10/SUM(Data!$J$2:$J$2379) -> 0.019968903
A11: 10 | B11: =LARGE(Data!$J$2:$J$2379,A11) -> 2340 | C11: =C10+B11 -> 26690 | D11: =C11/SUM(Data!$J$2:$J$2379) -> 0.021887885
A12: 11 | B12: =LARGE(Data!$J$2:$J$2379,A12) -> 2250 | C12: =C11+B12 -> 28940 | D12: =C12/SUM(Data!$J$2:$J$2379) -> 0.023733061
A13: 12 | B13: =LARGE(Data!$J$2:$J$2379,A13) -> 2210 | C13: =C12+B13 -> 31150 | D13: =C13/SUM(Data!$J$2:$J$2379) -> 0.025545434
A14: 13 | B14: =LARGE(Data!$J$2:$J$2379,A14) -> 2210 | C14: =C13+B14 -> 33360 | D14: =C14/SUM(Data!$J$2:$J$2379) -> 0.027357807
... A2379: 2378 | B2379: =LARGE(Data!$J$2:$J$2379,A2379) -> 30 | C2379: =C2378+B2379 -> 1219396 | D2379: =C2379/SUM(Data!$J$2:$J$2379) -> 1
